odoo/addons/l10n_cl_etd_account/README.rst
odoo/addons/l10n_cl_etd_account/__init__.py
odoo/addons/l10n_cl_etd_account/__manifest__.py
odoo/addons/l10n_cl_etd_account/data/etd_document.xml
odoo/addons/l10n_cl_etd_account/data/etd_document_file.xml
odoo/addons/l10n_cl_etd_account/i18n/es_CL.po
odoo/addons/l10n_cl_etd_account/i18n/l10n_cl_etd_account.pot
odoo/addons/l10n_cl_etd_account/models/__init__.py
odoo/addons/l10n_cl_etd_account/models/account_invoice.py
odoo/addons/l10n_cl_etd_account/models/etd_document.py
odoo/addons/l10n_cl_etd_account/readme/CONFIGURE.rst
odoo/addons/l10n_cl_etd_account/readme/CONTRIBUTORS.rst
odoo/addons/l10n_cl_etd_account/readme/DESCRIPTION.rst
odoo/addons/l10n_cl_etd_account/readme/USAGE.rst
odoo/addons/l10n_cl_etd_account/security/ir.model.access.csv
odoo/addons/l10n_cl_etd_account/static/description/icon.png
odoo/addons/l10n_cl_etd_account/static/description/index.html
odoo/addons/l10n_cl_etd_account/static/xml/invoice.xml
odoo/addons/l10n_cl_etd_account/static/xml/ticket.xml
odoo/addons/l10n_cl_etd_account/static/xsd/DTE_v10.xsd
odoo/addons/l10n_cl_etd_account/static/xsd/EnvioBOLETA_v11.xsd
odoo/addons/l10n_cl_etd_account/static/xsd/EnvioDTE_v10.xsd
odoo/addons/l10n_cl_etd_account/static/xsd/SiiTypes_v10.xsd
odoo/addons/l10n_cl_etd_account/static/xsd/xmldsignature_v10.xsd
odoo/addons/l10n_cl_etd_account/views/account_invoice.xml
odoo/addons/l10n_cl_etd_account/wizard/__init__.py
odoo/addons/l10n_cl_etd_account/wizard/account_invoice_refund.py
odoo12_addon_l10n_cl_etd_account-12.0.2.1.0.dist-info/METADATA
odoo12_addon_l10n_cl_etd_account-12.0.2.1.0.dist-info/WHEEL
odoo12_addon_l10n_cl_etd_account-12.0.2.1.0.dist-info/top_level.txt
odoo12_addon_l10n_cl_etd_account-12.0.2.1.0.dist-info/RECORD
