Metadata-Version: 2.1
Name: odoo12-addon-l10n-cl-etd-account
Version: 12.0.2.1.0
Summary: Sign your invoices and send them to SII.
Home-page: https://github.com/OCA/l10n-chile
Author: Daniel Santibáñez Polanco, Cooperativa OdooCoop, Konos, Open Source Integrators, Odoo Community Association (OCA)
Author-email: support@odoo-community.org
License: AGPL-3
Platform: UNKNOWN
Classifier: Programming Language :: Python
Classifier: Framework :: Odoo
Classifier: License :: OSI Approved :: GNU Affero General Public License v3
Classifier: Development Status :: 4 - Beta
Requires-Python: >=3.5
Requires-Dist: odoo12-addon-l10n-cl-chart-of-account
Requires-Dist: odoo12-addon-l10n-cl-etd
Requires-Dist: odoo12-addon-l10n-cl-invoicing-policy
Requires-Dist: odoo12-addon-l10n-cl-sii-reference-account
Requires-Dist: odoo (<12.1dev,>=12.0a)
